gaiah/__init__.py
gaiah/cli.py
gaiah/gaiah.py
gaiah/gaiah_commit.py
gaiah/gaiah_github.py
gaiah/gaiah_repo.py
gaiah/utils.py
gaiah/template/DEMO_README.md
gaiah/template/config.example.yml
gaiah/template/llm_commit_messages.md
gaiah/template/template.gitignore
gaiah_toolkit-0.6.3.dist-info/LICENSE
gaiah_toolkit-0.6.3.dist-info/METADATA
gaiah_toolkit-0.6.3.dist-info/WHEEL
gaiah_toolkit-0.6.3.dist-info/entry_points.txt
gaiah_toolkit-0.6.3.dist-info/top_level.txt
gaiah_toolkit-0.6.3.dist-info/RECORD
