Metadata-Version: 2.1
Name: gaiah_toolkit
Version: 0.6.3
Home-page: https://github.com/your_username/gaiah
Classifier: Development Status :: 3 - Alpha
Classifier: Intended Audience :: Developers
Classifier: Topic :: Software Development :: Version Control
License-File: LICENSE
Requires-Dist: gitpython
Requires-Dist: python-dotenv
Requires-Dist: PyGithub
Requires-Dist: termcolor
Requires-Dist: art
Requires-Dist: pyyaml
